gnip_insights_interface/__init__.py
gnip_insights_interface/audience_api.py
gnip_insights_interface/engagement_api.py
gnip_insights_interface/exceptions.py
gnip_insights_interface/utils.py
gnip_insights_interface-0.2.data/scripts/audience_insights.py
gnip_insights_interface-0.2.data/scripts/tweet_engagements.py
gnip_insights_interface-0.2.dist-info/DESCRIPTION.rst
gnip_insights_interface-0.2.dist-info/METADATA
gnip_insights_interface-0.2.dist-info/RECORD
gnip_insights_interface-0.2.dist-info/WHEEL
gnip_insights_interface-0.2.dist-info/metadata.json
gnip_insights_interface-0.2.dist-info/top_level.txt
